vpop_calibration/__init__.py
vpop_calibration/data_generation.py
vpop_calibration/diagnostics.py
vpop_calibration/model/__init__.py
vpop_calibration/model/data.py
vpop_calibration/model/gp.py
vpop_calibration/model/plot.py
vpop_calibration/nlme.py
vpop_calibration/ode.py
vpop_calibration/saem.py
vpop_calibration/structural_model.py
vpop_calibration/test/__init__.py
vpop_calibration/test/analytical/test_analytical_saem.py
vpop_calibration/test/conftest.py
vpop_calibration/test/gp/test_data_loading.py
vpop_calibration/test/gp/test_gp_flavors.py
vpop_calibration/test/gp/test_gp_saem.py
vpop_calibration/test/ode/test_data_generation.py
vpop_calibration/test/ode/test_ode_saem.py
vpop_calibration/utils.py
vpop_calibration/vpop.py
vpop_calibration-2.5.1.dist-info/METADATA
vpop_calibration-2.5.1.dist-info/WHEEL
vpop_calibration-2.5.1.dist-info/licenses/LICENSE
vpop_calibration-2.5.1.dist-info/RECORD
