Metadata-Version: 2.4
Name: vpop-calibration
Version: 2.5.1
Summary: 
License-File: LICENSE
Author: Paul Lemarre
Author-email: paul.lemarre@novainsilico.ai
Requires-Python: >=3.12,<4.0
Classifier: Programming Language :: Python :: 3
Classifier: Programming Language :: Python :: 3.12
Classifier: Programming Language :: Python :: 3.13
Classifier: Programming Language :: Python :: 3.14
Requires-Dist: gpytorch (>=1.14.2,<2.0.0)
Requires-Dist: matplotlib (>=3.10.7,<4.0.0)
Requires-Dist: numpy (>=2.3.4,<3.0.0)
Requires-Dist: pandas (>=2.3.3,<3.0.0)
Requires-Dist: plotly (>=6.4.0,<7.0.0)
Requires-Dist: scipy (>=1.16.3,<2.0.0)
Requires-Dist: torch
Requires-Dist: tqdm (>=4.67.1,<5.0.0)
Requires-Dist: uuid (>=1.30,<2.0)
